AUTHORS
LICENSE
README.md
setup.py
fast_hadamard_transform/__init__.py
fast_hadamard_transform/fast_hadamard_transform_interface.py
fast_hadamard_transform.egg-info/PKG-INFO
fast_hadamard_transform.egg-info/SOURCES.txt
fast_hadamard_transform.egg-info/dependency_links.txt
fast_hadamard_transform.egg-info/requires.txt
fast_hadamard_transform.egg-info/top_level.txt