Metadata-Version: 2.1
Name: fast-hadamard-transform
Version: 1.0.0.post1
Summary: Fast Hadamard Transform in CUDA, with a PyTorch interface
Home-page: https://github.com/Dao-AILab/fast-hadamard-transform
Author: Tri Dao
Author-email: trid@cs.stanford.edu
Classifier: Programming Language :: Python :: 3
Classifier: License :: OSI Approved :: BSD License
Classifier: Operating System :: Unix
Requires-Python: >=3.7
License-File: LICENSE
License-File: AUTHORS
